DlxTestPacksetup.py
README.txt
DlxTestPack/DlxTestClassV5.py
DlxTestPack/InI_DealV2.py
DlxTestPack/__init__.py
DlxTestPack/pack.py
DlxTestPack.egg-info/PKG-INFO
DlxTestPack.egg-info/SOURCES.txt
DlxTestPack.egg-info/dependency_links.txt
DlxTestPack.egg-info/requires.txt
DlxTestPack.egg-info/top_level.txt
DlxTestPack/DlxEnhanced/CMW500.py
DlxTestPack/DlxEnhanced/P66391D.py
DlxTestPack/DlxEnhanced/SP9500.py
DlxTestPack/DlxEnhanced/UXM.py
DlxTestPack/DlxEnhanced/__init__.py
DlxTestPack/DlxEnhanced/NB500Enhanced/NB.py
DlxTestPack/DlxEnhanced/NB500Enhanced/__init__.py
DlxTestPack/TkPackByMe/__init__.py
DlxTestPack/TkPackByMe/fix.py
DlxTestPack/TkPackByMe/guiFrame.py
DlxTestPack/TkPackByMe/sqlite_api.py
DlxTestPack/TkPackByMe/time_test.py