Metadata-Version: 2.1
Name: DlxTestPack
Version: 1.3
Summary: UsedForSimcom AutoTest,Used environment python3.8.10
Home-page: https://www.cnblogs.com/hardfood
Author: hardfood
Author-email: mdzzdyxc@163.com
License: UNKNOWN
Platform: UNKNOWN
